friendly_data_registry/__init__.py
friendly_data_registry/cols/__init__.py
friendly_data_registry/cols/capacity_factor.json
friendly_data_registry/cols/description.json
friendly_data_registry/cols/flow_in.yaml
friendly_data_registry/cols/flow_out.yaml
friendly_data_registry/cols/name.json
friendly_data_registry/cols/nameplate_capacity.yaml
friendly_data_registry/cols/storage_capacity.yaml
friendly_data_registry/cols/value.json
friendly_data_registry/idxcols/__init__.py
friendly_data_registry/idxcols/carrier.json
friendly_data_registry/idxcols/model.json
friendly_data_registry/idxcols/region.yaml
friendly_data_registry/idxcols/scenario.json
friendly_data_registry/idxcols/technology.yaml
friendly_data_registry/idxcols/timestep.json
friendly_data_registry/idxcols/unit.yaml
friendly_data_registry/idxcols/variable.yaml
friendly_data_registry/idxcols/year.json
friendly_data_registry-20220103.dist-info/LICENSE
friendly_data_registry-20220103.dist-info/METADATA
friendly_data_registry-20220103.dist-info/WHEEL
friendly_data_registry-20220103.dist-info/top_level.txt
friendly_data_registry-20220103.dist-info/RECORD
